INSTALL
LICENSE
MANIFEST.in
README.rst
setup.cfg
setup.py
scrapy_rotated_proxy/VERSION
scrapy_rotated_proxy/__init__.py
scrapy_rotated_proxy/signals.py
scrapy_rotated_proxy/util.py
scrapy_rotated_proxy.egg-info/PKG-INFO
scrapy_rotated_proxy.egg-info/SOURCES.txt
scrapy_rotated_proxy.egg-info/dependency_links.txt
scrapy_rotated_proxy.egg-info/not-zip-safe
scrapy_rotated_proxy.egg-info/requires.txt
scrapy_rotated_proxy.egg-info/top_level.txt
scrapy_rotated_proxy/downloadmiddlewares/__init__.py
scrapy_rotated_proxy/downloadmiddlewares/proxy.py
scrapy_rotated_proxy/extensions/__init__.py
scrapy_rotated_proxy/extensions/base_storage.py
scrapy_rotated_proxy/extensions/default_settings.py
scrapy_rotated_proxy/extensions/file_storage.py
scrapy_rotated_proxy/extensions/mongodb_storage.py
tests/__init__.py
tests/py3-ignores.txt
tests/requirements-py3.txt
tests/requirements.txt
tests/test_downloadermiddleware_httpproxy.py