Metadata-Version: 1.1
Name: scrapy-rotated-proxy
Version: 0.0.6
Summary: A middleware to change proxy rotated for Scrapy
Home-page: https://github.com/xiaowangwindow/scrapy-rotated-proxy
Author: Alex Wang
Author-email: xiaowangwindow@163.com
License: BSD
Platform: UNKNOWN
Classifier: Framework :: Scrapy
Classifier: Development Status :: 2 - Pre-Alpha
Classifier: Environment :: Plugins
Classifier: Intended Audience :: Developers
Classifier: License :: OSI Approved :: BSD License
Classifier: Operating System :: OS Independent
Classifier: Programming Language :: Python
Classifier: Programming Language :: Python :: 2
Classifier: Programming Language :: Python :: 2.7
Classifier: Programming Language :: Python :: 3
Classifier: Programming Language :: Python :: 3.3
Classifier: Programming Language :: Python :: 3.4
Classifier: Programming Language :: Python :: 3.5
Classifier: Programming Language :: Python :: 3.6
Classifier: Topic :: Internet :: WWW/HTTP
Classifier: Topic :: Software Development :: Libraries :: Python Modules
